CHANGES.txt
Makefile
README.txt
setup.cfg
setup.py
src/repoze/__init__.py
src/repoze.bfg.skins.egg-info/PKG-INFO
src/repoze.bfg.skins.egg-info/SOURCES.txt
src/repoze.bfg.skins.egg-info/dependency_links.txt
src/repoze.bfg.skins.egg-info/namespace_packages.txt
src/repoze.bfg.skins.egg-info/not-zip-safe
src/repoze.bfg.skins.egg-info/requires.txt
src/repoze.bfg.skins.egg-info/top_level.txt
src/repoze/bfg/__init__.py
src/repoze/bfg/skins/__init__.py
src/repoze/bfg/skins/configuration.py
src/repoze/bfg/skins/configure.zcml
src/repoze/bfg/skins/interfaces.py
src/repoze/bfg/skins/meta.zcml
src/repoze/bfg/skins/models.py
src/repoze/bfg/skins/routes.py
src/repoze/bfg/skins/zcml.py
src/repoze/bfg/skins/zpt.py
src/repoze/bfg/skins/docs/conf.py
src/repoze/bfg/skins/docs/extending.rst
src/repoze/bfg/skins/docs/glossary.rst
src/repoze/bfg/skins/docs/index.rst
src/repoze/bfg/skins/docs/registration.rst
src/repoze/bfg/skins/docs/routing.rst
src/repoze/bfg/skins/docs/templates.rst
src/repoze/bfg/skins/tests/__init__.py
src/repoze/bfg/skins/tests/test_doctests.py
src/repoze/bfg/skins/tests/alt_skins/main_template.pt
src/repoze/bfg/skins/tests/skins/index.pt
src/repoze/bfg/skins/tests/skins/main_template.pt
src/repoze/bfg/skins/tests/skins/about/index.pt
src/repoze/bfg/skins/tests/skins/about/images/logo.png
src/repoze/bfg/skins/tests/skins/images/logo.png